LICENCE
MANIFEST.in
README.md
setup.py
fabpowertasks/__init__.py
fabpowertasks/commands.py
fabpowertasks/config.py
fabpowertasks/deploy.py
fabpowertasks/testing.py
fabpowertasks/util.py
fabpowertasks/vagrant.py
fabpowertasks.egg-info/PKG-INFO
fabpowertasks.egg-info/SOURCES.txt
fabpowertasks.egg-info/dependency_links.txt
fabpowertasks.egg-info/requires.txt
fabpowertasks.egg-info/top_level.txt